pexels_python/__init__.py
pexels_python/core/__init__.py
pexels_python/core/async_client.py
pexels_python/core/cache.py
pexels_python/core/client.py
pexels_python/core/exceptions.py
pexels_python/core/pagination.py
pexels_python/core/retry.py
pexels_python/schemas/__init__.py
pexels_python/schemas/common.py
pexels_python/schemas/photos.py
pexels_python/schemas/videos.py
pexels_python/utils/__init__.py
pexels_python/utils/logging.py
pexels_python-0.1.0.dist-info/METADATA
pexels_python-0.1.0.dist-info/WHEEL
pexels_python-0.1.0.dist-info/RECORD
