Metadata-Version: 2.3
Name: pexels-python
Version: 0.1.0
Summary: A Pexels Python API client library
Author: coralera
Author-email: haoyue@coralera.org
Requires-Python: >=3.11,<4
Classifier: Programming Language :: Python :: 3
Classifier: Programming Language :: Python :: 3.11
Classifier: Programming Language :: Python :: 3.12
Classifier: Programming Language :: Python :: 3.13
Requires-Dist: anyio (>=4.10.0,<5.0.0)
Requires-Dist: httpx (>=0.28.1,<0.29.0)
Requires-Dist: python-dotenv (>=1.1.1,<2.0.0)
Requires-Dist: redis (>=6.4.0,<7.0.0)
Requires-Dist: requests (>=2.32.4,<3.0.0)
Requires-Dist: rich (>=14.1.0,<15.0.0)
Requires-Dist: sniffio (>=1.3.1,<2.0.0)
